Metadata-Version: 2.1
Name: simple-test-default-reporter
Version: 0.3.0
Summary: The default reporter for simple_test
Home-page: https://github.com/olsonpm/py_simple-test-default-reporter
Author: Philip Olson
Author-email: philip.olson@pm.me
Requires-Python: >=3.7,<4.0
Classifier: Programming Language :: Python :: 3
Classifier: Programming Language :: Python :: 3.7
Project-URL: Repository, https://github.com/olsonpm/py_simple-test-default-reporter
